prtpy/VERSION
prtpy/__init__.py
prtpy/binners.py
prtpy/inclusion_exclusion_tree.py
prtpy/objectives.py
prtpy/outputtypes.py
prtpy/packing/__init__.py
prtpy/packing/adaptors.py
prtpy/packing/best_fit.py
prtpy/packing/bin_completion.py
prtpy/packing/bin_completion_utils.py
prtpy/packing/cflz_covering.py
prtpy/packing/first_fit.py
prtpy/packing/greedy_covering.py
prtpy/partitioning/Horowitz_And_Sahni.py
prtpy/partitioning/Schroeppel_Shamir.py
prtpy/partitioning/__init__.py
prtpy/partitioning/adaptors.py
prtpy/partitioning/balanced.py
prtpy/partitioning/cbldm.py
prtpy/partitioning/complete_greedy.py
prtpy/partitioning/complete_karmarkar_karp.py
prtpy/partitioning/dynamic_programming.py
prtpy/partitioning/greedy.py
prtpy/partitioning/integer_programming.py
prtpy/partitioning/integer_programming_avg.py
prtpy/partitioning/karmarkar_karp.py
prtpy/partitioning/multifit.py
prtpy/partitioning/recursive_number_partitioning_korf.py
prtpy/partitioning/recursive_number_partitioning_moffitt.py
prtpy/partitioning/roundrobin.py
prtpy/partitioning/sequential_number_partitioning.py
prtpy-0.8.3.dist-info/LICENSE
prtpy-0.8.3.dist-info/METADATA
prtpy-0.8.3.dist-info/WHEEL
prtpy-0.8.3.dist-info/top_level.txt
prtpy-0.8.3.dist-info/RECORD
