Metadata-Version: 2.1
Name: prtpy
Version: 0.8.3
Summary: Number partitioning in Python
Home-page: https://github.com/erelsgl/prtpy
Author: Erel Segal-Halevi
Author-email: erelsgl@gmail.com
License: MIT
Project-URL: Bug Reports, https://github.com/erelsgl/prtpy/issues
Project-URL: Source Code, https://github.com/erelsgl/prtpy
Keywords: optimization,partition
Classifier: Development Status :: 2 - Pre-Alpha
Requires-Python: >=3.8
License-File: LICENSE
Requires-Dist: numpy>=1.21.3
Requires-Dist: scipy>=1.6.1
Requires-Dist: mip>=1.13.0
Provides-Extra: simulations
Requires-Dist: experiments_csv[plotting]>=0.5.0; extra == "simulations"
